authorship/__init__.py
authorship/admin.py
authorship/apps.py
authorship/factories.py
authorship/forms.py
authorship/models.py
authorship/py.typed
authorship/settings.py
authorship/utils.py
authorship/views.py
authorship/api/__init__.py
authorship/api/views.py
thecut/authorship/__init__.py
thecut/authorship/admin.py
thecut/authorship/apps.py
thecut/authorship/factories.py
thecut/authorship/forms.py
thecut/authorship/models.py
thecut/authorship/py.typed
thecut/authorship/settings.py
thecut/authorship/utils.py
thecut/authorship/views.py
thecut/authorship/api/__init__.py
thecut/authorship/api/views.py
django_authorship-2.0.0.dist-info/LICENSE
django_authorship-2.0.0.dist-info/METADATA
django_authorship-2.0.0.dist-info/WHEEL
django_authorship-2.0.0.dist-info/top_level.txt
django_authorship-2.0.0.dist-info/RECORD
