Metadata-Version: 2.1
Name: django-authorship
Version: 2.0.0
Summary: A set of Django mixins to easily record authorship information for your models.
Home-page: https://gitlab.com/django-authorship/django-authorship
Author: Matt Austin
Author-email: devops@mattaustin.com.au
License: Apache 2.0
Project-URL: Documentation, https://django-authorship.readthedocs.io/en/latest/
Project-URL: Changelog, https://django-authorship.readthedocs.io/en/latest/history.html
Project-URL: Issues, https://gitlab.com/django-authorship/django-authorship/issues
Project-URL: Source, https://gitlab.com/django-authorship/django-authorship
Keywords: django,authorship,created,updated,model,mixin
Platform: UNKNOWN
Classifier: Development Status :: 5 - Production/Stable
Classifier: Environment :: Web Environment
Classifier: Framework :: Django
Classifier: Framework :: Django :: 2.2
Classifier: Framework :: Django :: 3.1
Classifier: Framework :: Django :: 3.2
Classifier: Intended Audience :: Developers
Classifier: License :: OSI Approved :: Apache Software License
Classifier: Operating System :: OS Independent
Classifier: Programming Language :: Python
Classifier: Programming Language :: Python :: 3
Classifier: Programming Language :: Python :: 3.6
Classifier: Programming Language :: Python :: 3.7
Classifier: Programming Language :: Python :: 3.8
Classifier: Programming Language :: Python :: 3.9
Classifier: Programming Language :: Python :: 3.10
Classifier: Topic :: Internet :: WWW/HTTP :: Dynamic Content
Classifier: Topic :: Software Development :: Libraries :: Python Modules
Classifier: Topic :: Software Development :: Libraries :: Application Frameworks
Requires-Python: >=3.6
License-File: LICENSE
Requires-Dist: django (!=3.0.*,>=2.2)
Provides-Extra: docs
Requires-Dist: djangorestframework (<4,>=3) ; extra == 'docs'
Requires-Dist: factory-boy (~=3.2) ; extra == 'docs'
Requires-Dist: sphinx (~=4.2) ; extra == 'docs'
Requires-Dist: sphinx-rtd-theme (~=1.0) ; extra == 'docs'
Provides-Extra: tests
Requires-Dist: coverage (~=6.0) ; extra == 'tests'
Requires-Dist: factory-boy (~=3.2) ; extra == 'tests'
Requires-Dist: freezegun (~=1.1) ; extra == 'tests'
Requires-Dist: unittest-xml-reporting (~=3.0) ; extra == 'tests'
Provides-Extra: types
Requires-Dist: django-stubs (~=1.7) ; extra == 'types'
Requires-Dist: mypy (==0.910) ; extra == 'types'
